deep_merge/__init__.py
deep_merge/about.py
deep_merge/merge.py
deep_merge/tests/__init__.py
deep_merge/tests/test_merge.py
deep_merge-0.0.4.dist-info/DESCRIPTION.rst
deep_merge-0.0.4.dist-info/METADATA
deep_merge-0.0.4.dist-info/RECORD
deep_merge-0.0.4.dist-info/WHEEL
deep_merge-0.0.4.dist-info/metadata.json
deep_merge-0.0.4.dist-info/top_level.txt
