Metadata-Version: 2.0
Name: deep-merge
Version: 0.0.4
Summary: A simple utility for merging python dictionaries.
Home-page: https://github.com/halfak/deep_merge
Author: Aaron Halfaker
Author-email: aaron.halfaker@gmail.com
License: MIT
Platform: UNKNOWN
Classifier: Programming Language :: Python
Classifier: Environment :: Other Environment
Classifier: Intended Audience :: Developers
Classifier: License :: OSI Approved :: MIT License
Classifier: Operating System :: OS Independent
Classifier: Topic :: Software Development :: Libraries :: Python Modules
